{
    "text": "Less than two weeks away from losing its federal funding, Casa Alitas has already cut its staff dramatically.",
    "title": "Intel, better jobs, economy, Joe Biden, J.D. Wallace, Biden in Phoenix, President comes to Arizona, [Video] \u2013 Brand Marketing",
    "date": "2024-03-21T08:27:00.000+02:00",
    "url": "https://brandmarketingready.com/intel-better-jobs-economy-joe-biden-j-d-wallace-biden-in-phoenix-president-comes-to-arizona-video",
    "author": "Post author By Curator"
}