{
    "text": "Mr. Trump did pad his campaign\u2019s account in February, adding more than $3 million to the cash on hand since January, when he ended the month with about $30 million on hand. But Mr. Biden\u2019s campaign, which ended January with $56 million on hand, added $15 million in February.",
    "title": "Biden Widens His Financial Lead Over Trump",
    "date": "2024-03-21T08:48:00.000+02:00",
    "url": "https://www.golignews.com.tr/biden-widens-his-financial-lead-over-trump.html",
    "author": "Golignews"
}