{
    "text": "Manchin Vows to Block Biden Judge Picks\n\nSen. Joe Manchin, D-W.Va., said he will not support President Joe Biden's judicial picks who don't have any Republican support. Manchin, who's not \u2026\n\nRead more on newsmax.com",
    "title": "Manchin Vows to Block Biden Judge Picks | Flipboard",
    "date": "2024-03-21T21:40:00.000+02:00",
    "url": "https://flipboard.com/article/manchin-vows-to-block-biden-judge-picks/f-66bd56a680%2Fnewsmax.com",
    "author": "newsmax.com - Charlie McCarthy"
}